{
  "success": true,
  "data": [
    {
      "_id": {
        "$id": "20260506844"
      },
      "id": "20260506844",
      "coords": true,
      "dateTime": {
        "sec": 1775719500
      },
      "date": "09-04-2026",
      "hour": "08:25",
      "location": "Viseu, Vouzela, Alcofra",
      "aerial": 0,
      "meios_aquaticos": 0,
      "man": 18,
      "terrain": 5,
      "district": "Viseu",
      "concelho": "Vouzela",
      "freguesia": "Alcofra",
      "dico": "1824",
      "lat": 40.603892,
      "lng": -8.160315,
      "naturezaCode": "3109",
      "natureza": "Gestão de Combustível",
      "especieName": null,
      "familiaName": null,
      "statusCode": 7,
      "statusColor": "6ABF59",
      "status": "Em Resolução",
      "important": false,
      "localidade": "Alcofra ",
      "active": true,
      "sadoId": "20260506844",
      "sharepointId": 27028862,
      "extra": null,
      "disappear": false,
      "icnf": null,
      "detailLocation": null,
      "kml": null,
      "kmlVost": null,
      "pco": null,
      "cos": null,
      "heliFight": 0,
      "heliCoord": 0,
      "planeFight": 0,
      "anepcDirectUpdate": false,
      "regiao": "Centro",
      "sub_regiao": "Viseu Dão Lafões",
      "nearestWeatherStationId": 6213021,
      "weather": null,
      "created": {
        "sec": 1775719936
      },
      "updated": {
        "sec": 1775750173
      }
    },
    {
      "_id": {
        "$id": "20260507552"
      },
      "id": "20260507552",
      "coords": true,
      "dateTime": {
        "sec": 1775726700
      },
      "date": "09-04-2026",
      "hour": "10:25",
      "location": "Viana Do Castelo, Paredes de Coura, Insalde E Porreiras",
      "aerial": 0,
      "meios_aquaticos": 0,
      "man": 9,
      "terrain": 3,
      "district": "Viana Do Castelo",
      "concelho": "Paredes De Coura",
      "freguesia": "Insalde E Porreiras",
      "dico": "1605",
      "lat": 41.955907,
      "lng": -8.550788,
      "naturezaCode": "3109",
      "natureza": "Gestão de Combustível",
      "especieName": null,
      "familiaName": null,
      "statusCode": 5,
      "statusColor": "B81E1F",
      "status": "Em Curso",
      "important": false,
      "localidade": "Espigueiros ",
      "active": true,
      "sadoId": "20260507552",
      "sharepointId": 27029570,
      "extra": null,
      "disappear": false,
      "icnf": null,
      "detailLocation": null,
      "kml": null,
      "kmlVost": null,
      "pco": null,
      "cos": null,
      "heliFight": 0,
      "heliCoord": 0,
      "planeFight": 0,
      "anepcDirectUpdate": false,
      "regiao": "Norte",
      "sub_regiao": "Alto Minho",
      "nearestWeatherStationId": 6211213,
      "weather": {
        "stationId": 6211213,
        "stationLocation": "Paredes De Coura - Vascões (CIM)",
        "temperatura": 21.1,
        "humidade": 53,
        "intensidadeVento": 3.1,
        "intensidadeVentoKM": 11.2,
        "idDireccVento": 1,
        "direccVento": "N",
        "precAcumulada": null,
        "radiacao": 4606.3,
        "pressao": 1016.8,
        "date": "2026-04-09T14:00:00.000000Z"
      },
      "created": {
        "sec": 1775727019
      },
      "updated": {
        "sec": 1775742033
      }
    },
    {
      "_id": {
        "$id": "20260508874"
      },
      "id": "20260508874",
      "coords": true,
      "dateTime": {
        "sec": 1775742480
      },
      "date": "09-04-2026",
      "hour": "14:48",
      "location": "Aveiro, Vale de Cambra, Vila Chã, Codal E Vila Cova De Perrinho",
      "aerial": 0,
      "meios_aquaticos": 0,
      "man": 20,
      "terrain": 7,
      "district": "Aveiro",
      "concelho": "Vale De Cambra",
      "freguesia": "Vila Chã, Codal E Vila Cova De Perrinho",
      "dico": "0119",
      "lat": 40.89383,
      "lng": -8.394087,
      "naturezaCode": "3103",
      "natureza": "Mato",
      "especieName": null,
      "familiaName": null,
      "statusCode": 7,
      "statusColor": "6ABF59",
      "status": "Em Resolução",
      "important": false,
      "localidade": " ",
      "active": true,
      "sadoId": "20260508874",
      "sharepointId": 27030892,
      "extra": null,
      "disappear": false,
      "icnf": {
        "altitude": 0,
        "fogacho": true,
        "fontealerta": "Bombeiros"
      },
      "detailLocation": "Vila Cova Perrinho (Souto)",
      "kml": null,
      "kmlVost": null,
      "pco": null,
      "cos": null,
      "heliFight": 0,
      "heliCoord": 0,
      "planeFight": 0,
      "anepcDirectUpdate": false,
      "regiao": "Norte",
      "sub_regiao": "Area M. Porto",
      "nearestWeatherStationId": 1210669,
      "weather": {
        "stationId": 1210669,
        "stationLocation": "Arouca",
        "temperatura": 26,
        "humidade": 44,
        "intensidadeVento": 1.5,
        "intensidadeVentoKM": 5.4,
        "idDireccVento": 3,
        "direccVento": "E",
        "precAcumulada": 0,
        "radiacao": 1921.7,
        "pressao": null,
        "date": "2026-04-09T15:00:00.000000Z"
      },
      "created": {
        "sec": 1775742863
      },
      "updated": {
        "sec": 1775748972
      }
    },
    {
      "_id": {
        "$id": "20260509085"
      },
      "id": "20260509085",
      "coords": true,
      "dateTime": {
        "sec": 1775744580
      },
      "date": "09-04-2026",
      "hour": "15:23",
      "location": "Castelo Branco, Fundão, Vale De Prazeres E Mata Da Rainha",
      "aerial": 0,
      "meios_aquaticos": 0,
      "man": 8,
      "terrain": 3,
      "district": "Castelo Branco",
      "concelho": "Fundão",
      "freguesia": "Vale De Prazeres E Mata Da Rainha",
      "dico": "0504",
      "lat": 40.118075,
      "lng": -7.356578,
      "naturezaCode": "3103",
      "natureza": "Mato",
      "especieName": null,
      "familiaName": null,
      "statusCode": 8,
      "statusColor": "BDBDBD",
      "status": "Conclusão",
      "important": false,
      "localidade": "Catrão ",
      "active": true,
      "sadoId": "20260509085",
      "sharepointId": 27031103,
      "extra": null,
      "disappear": false,
      "icnf": {
        "altitude": 0,
        "fogacho": true,
        "fontealerta": "Bombeiros"
      },
      "detailLocation": "Catrão",
      "kml": null,
      "kmlVost": null,
      "pco": null,
      "cos": null,
      "heliFight": 0,
      "heliCoord": 0,
      "planeFight": 0,
      "anepcDirectUpdate": false,
      "regiao": "Centro",
      "sub_regiao": "Beiras e Serra da Estrela",
      "nearestWeatherStationId": 1210698,
      "weather": {
        "stationId": 1210698,
        "stationLocation": "Fundão",
        "temperatura": 24.4,
        "humidade": 38,
        "intensidadeVento": 4.1,
        "intensidadeVentoKM": 14.8,
        "idDireccVento": 4,
        "direccVento": "SE",
        "precAcumulada": 0,
        "radiacao": null,
        "pressao": null,
        "date": "2026-04-09T15:00:00.000000Z"
      },
      "created": {
        "sec": 1775745134
      },
      "updated": {
        "sec": 1775747024
      }
    },
    {
      "_id": {
        "$id": "20260509188"
      },
      "id": "20260509188",
      "coords": true,
      "dateTime": {
        "sec": 1775745960
      },
      "date": "09-04-2026",
      "hour": "15:46",
      "location": "Braga, Vila Nova de Famalicão, Oliveira (santa Maria)",
      "aerial": 0,
      "meios_aquaticos": 0,
      "man": 5,
      "terrain": 1,
      "district": "Braga",
      "concelho": "Vila Nova De Famalicão",
      "freguesia": "Oliveira (santa Maria)",
      "dico": "0312",
      "lat": 41.402952,
      "lng": -8.419258,
      "naturezaCode": "3103",
      "natureza": "Mato",
      "especieName": null,
      "familiaName": null,
      "statusCode": 8,
      "statusColor": "BDBDBD",
      "status": "Conclusão",
      "important": false,
      "localidade": " ",
      "active": true,
      "sadoId": "20260509188",
      "sharepointId": 27031206,
      "extra": null,
      "disappear": false,
      "icnf": null,
      "detailLocation": null,
      "kml": null,
      "kmlVost": null,
      "pco": null,
      "cos": null,
      "heliFight": 0,
      "heliCoord": 0,
      "planeFight": 0,
      "anepcDirectUpdate": false,
      "regiao": "Norte",
      "sub_regiao": "Ave",
      "nearestWeatherStationId": null,
      "weather": null,
      "created": {
        "sec": 1775746183
      },
      "updated": {
        "sec": 1775747783
      }
    },
    {
      "_id": {
        "$id": "20260509180"
      },
      "id": "20260509180",
      "coords": true,
      "dateTime": {
        "sec": 1775745900
      },
      "date": "09-04-2026",
      "hour": "15:45",
      "location": "Braga, Fafe, Regadas",
      "aerial": 0,
      "meios_aquaticos": 0,
      "man": 7,
      "terrain": 2,
      "district": "Braga",
      "concelho": "Fafe",
      "freguesia": "Regadas",
      "dico": "0307",
      "lat": 41.402952,
      "lng": -8.139152,
      "naturezaCode": "3101",
      "natureza": "Povoamento Florestal",
      "especieName": null,
      "familiaName": null,
      "statusCode": 8,
      "statusColor": "BDBDBD",
      "status": "Conclusão",
      "important": false,
      "localidade": " ",
      "active": true,
      "sadoId": "20260509180",
      "sharepointId": 27031198,
      "extra": null,
      "disappear": false,
      "icnf": null,
      "detailLocation": null,
      "kml": null,
      "kmlVost": null,
      "pco": null,
      "cos": null,
      "heliFight": 0,
      "heliCoord": 0,
      "planeFight": 0,
      "anepcDirectUpdate": false,
      "regiao": "Norte",
      "sub_regiao": "Ave",
      "nearestWeatherStationId": 1210625,
      "weather": {
        "stationId": 1210625,
        "stationLocation": "Guimarães",
        "temperatura": 26.9,
        "humidade": 34,
        "intensidadeVento": null,
        "intensidadeVentoKM": null,
        "idDireccVento": 0,
        "direccVento": null,
        "precAcumulada": null,
        "radiacao": 2580.1,
        "pressao": 1015.4,
        "date": "2026-04-09T15:00:00.000000Z"
      },
      "created": {
        "sec": 1775746184
      },
      "updated": {
        "sec": 1775749935
      }
    },
    {
      "_id": {
        "$id": "20260509303"
      },
      "id": "20260509303",
      "coords": true,
      "dateTime": {
        "sec": 1775747340
      },
      "date": "09-04-2026",
      "hour": "16:09",
      "location": "Viseu, Viseu, São João De Lourosa",
      "aerial": 0,
      "meios_aquaticos": 0,
      "man": 11,
      "terrain": 3,
      "district": "Viseu",
      "concelho": "Viseu",
      "freguesia": "São João De Lourosa",
      "dico": "1823",
      "lat": 40.61233,
      "lng": -7.90548,
      "naturezaCode": "3103",
      "natureza": "Mato",
      "especieName": null,
      "familiaName": null,
      "statusCode": 7,
      "statusColor": "6ABF59",
      "status": "Em Resolução",
      "important": false,
      "localidade": "São João De Lourosa ",
      "active": true,
      "sadoId": "20260509303",
      "sharepointId": 27031321,
      "extra": null,
      "disappear": false,
      "icnf": null,
      "detailLocation": null,
      "kml": null,
      "kmlVost": null,
      "pco": null,
      "cos": null,
      "heliFight": 0,
      "heliCoord": 0,
      "planeFight": 0,
      "anepcDirectUpdate": false,
      "regiao": "Centro",
      "sub_regiao": "Viseu Dão Lafões",
      "nearestWeatherStationId": 1240675,
      "weather": null,
      "created": {
        "sec": 1775747651
      },
      "updated": {
        "sec": 1775750418
      }
    },
    {
      "_id": {
        "$id": "20260509359"
      },
      "id": "20260509359",
      "coords": true,
      "dateTime": {
        "sec": 1775748060
      },
      "date": "09-04-2026",
      "hour": "16:21",
      "location": "Castelo Branco, Penamacor, Aldeia Do Bispo, Águas E Aldeia De João Pires",
      "aerial": 0,
      "meios_aquaticos": 0,
      "man": 7,
      "terrain": 2,
      "district": "Castelo Branco",
      "concelho": "Penamacor",
      "freguesia": "Aldeia Do Bispo, Águas E Aldeia De João Pires",
      "dico": "0507",
      "lat": 40.103937,
      "lng": -7.202773,
      "naturezaCode": "3105",
      "natureza": "Agrícola",
      "especieName": null,
      "familiaName": null,
      "statusCode": 7,
      "statusColor": "6ABF59",
      "status": "Em Resolução",
      "important": false,
      "localidade": "Termas Da Fonte Santa ",
      "active": true,
      "sadoId": "20260509359",
      "sharepointId": 27031377,
      "extra": null,
      "disappear": false,
      "icnf": null,
      "detailLocation": null,
      "kml": null,
      "kmlVost": null,
      "pco": null,
      "cos": null,
      "heliFight": 0,
      "heliCoord": 0,
      "planeFight": 0,
      "anepcDirectUpdate": false,
      "regiao": "Centro",
      "sub_regiao": "Beira Baixa",
      "nearestWeatherStationId": 1210687,
      "weather": {
        "stationId": 1210687,
        "stationLocation": "Covilhã (Aeródromo)",
        "temperatura": 25.1,
        "humidade": 39,
        "intensidadeVento": 3.7,
        "intensidadeVentoKM": 13.3,
        "idDireccVento": 2,
        "direccVento": "NE",
        "precAcumulada": null,
        "radiacao": 2689,
        "pressao": null,
        "date": "2026-04-09T15:00:00.000000Z"
      },
      "created": {
        "sec": 1775748375
      },
      "updated": {
        "sec": 1775750533
      }
    }
  ]
}
