{
  "success": true,
  "data": [
    {
      "_id": {
        "$id": "6520fc5a82fa29684412f55e"
      },
      "id": "20231238971",
      "coords": true,
      "dateTime": {
        "sec": 1696660200
      },
      "date": "07-10-2023",
      "hour": "07:30",
      "location": "Porto, Santo Tirso, Areias, Sequeiró, Lama E Palmeira",
      "aerial": 0,
      "meios_aquaticos": 0,
      "man": 7,
      "terrain": 2,
      "district": "Porto",
      "concelho": "Santo Tirso",
      "freguesia": "Areias, Sequeiró, Lama E Palmeira",
      "dico": "1314",
      "lat": 41.357122,
      "lng": -8.474703,
      "naturezaCode": "3103",
      "natureza": "Mato",
      "especieName": null,
      "familiaName": null,
      "statusCode": 7,
      "statusColor": "6ABF59",
      "status": "Em Resolução",
      "important": false,
      "localidade": "União Das Freguesias De Areias, Sequeiró, Lama E Palmeira ",
      "active": true,
      "sadoId": "20231238971",
      "sharepointId": 22745488,
      "extra": null,
      "disappear": false,
      "icnf": {
        "burnArea": {
          "povoamento": 0,
          "agricola": 0,
          "mato": 0.002,
          "total": 0.002
        },
        "altitude": 50.2925,
        "fogacho": true,
        "fontealerta": "112"
      },
      "detailLocation": "Espaço Industrial da Palmeira. Rua Parque Industrial. 4780-361 Santo Tirso. Portugal (Torre)",
      "kml": null,
      "kmlVost": null,
      "pco": null,
      "cos": null,
      "heliFight": 0,
      "heliCoord": 0,
      "planeFight": 0,
      "anepcDirectUpdate": false,
      "regiao": "Norte",
      "sub_regiao": "Area M. Porto",
      "created": {
        "sec": 1696660570
      },
      "updated": {
        "sec": 1696662249
      }
    },
    {
      "_id": {
        "$id": "65210882bf0f0458f717a59e"
      },
      "id": "20231239085",
      "coords": true,
      "dateTime": {
        "sec": 1696662540
      },
      "date": "07-10-2023",
      "hour": "08:09",
      "location": "Porto, Gondomar, Foz Do Sousa E Covelo",
      "aerial": 0,
      "meios_aquaticos": 0,
      "man": 15,
      "terrain": 4,
      "district": "Porto",
      "concelho": "Gondomar",
      "freguesia": "Foz Do Sousa E Covelo",
      "dico": "1304",
      "lat": 41.074755,
      "lng": -8.507907,
      "naturezaCode": "3103",
      "natureza": "Mato",
      "especieName": null,
      "familiaName": null,
      "statusCode": 7,
      "statusColor": "6ABF59",
      "status": "Em Resolução",
      "important": false,
      "localidade": " ",
      "active": true,
      "sadoId": "20231239085",
      "sharepointId": 22745602,
      "extra": null,
      "disappear": false,
      "icnf": null,
      "detailLocation": null,
      "kml": null,
      "kmlVost": null,
      "pco": null,
      "cos": null,
      "heliFight": 0,
      "heliCoord": 0,
      "planeFight": 0,
      "anepcDirectUpdate": false,
      "regiao": "Norte",
      "sub_regiao": "Area M. Porto",
      "created": {
        "sec": 1696663682
      },
      "updated": {
        "sec": 1696665844
      }
    },
    {
      "_id": {
        "$id": "65210cc8bf0f0458f717a5a4"
      },
      "id": "20231239190",
      "coords": true,
      "dateTime": {
        "sec": 1696664460
      },
      "date": "07-10-2023",
      "hour": "08:41",
      "location": "Viseu, Viseu, Cota",
      "aerial": 0,
      "meios_aquaticos": 0,
      "man": 7,
      "terrain": 2,
      "district": "Viseu",
      "concelho": "Viseu",
      "freguesia": "Cota",
      "dico": "1823",
      "lat": 40.798176,
      "lng": -7.811442,
      "naturezaCode": "3103",
      "natureza": "Mato",
      "especieName": null,
      "familiaName": null,
      "statusCode": 8,
      "statusColor": "BDBDBD",
      "status": "Conclusão",
      "important": false,
      "localidade": "Salgueiral ",
      "active": true,
      "sadoId": "20231239190",
      "sharepointId": 22745707,
      "extra": null,
      "disappear": false,
      "icnf": null,
      "detailLocation": null,
      "kml": null,
      "kmlVost": null,
      "pco": null,
      "cos": null,
      "heliFight": 0,
      "heliCoord": 0,
      "planeFight": 0,
      "anepcDirectUpdate": false,
      "regiao": "Centro",
      "sub_regiao": "Viseu Dão Lafões",
      "created": {
        "sec": 1696664776
      },
      "updated": {
        "sec": 1696668489
      }
    },
    {
      "_id": {
        "$id": "652118054192d852bd262752"
      },
      "id": "20231239411",
      "coords": true,
      "dateTime": {
        "sec": 1696667520
      },
      "date": "07-10-2023",
      "hour": "09:32",
      "location": "Porto, Amarante, Louredo",
      "aerial": 1,
      "meios_aquaticos": 0,
      "man": 16,
      "terrain": 2,
      "district": "Porto",
      "concelho": "Amarante",
      "freguesia": "Louredo",
      "dico": "1301",
      "lat": 41.258422,
      "lng": -8.135475,
      "naturezaCode": "3103",
      "natureza": "Mato",
      "especieName": null,
      "familiaName": null,
      "statusCode": 5,
      "statusColor": "B81E1F",
      "status": "Em Curso",
      "important": false,
      "localidade": "Louredo ",
      "active": true,
      "sadoId": "20231239411",
      "sharepointId": 22745928,
      "extra": null,
      "disappear": false,
      "icnf": null,
      "detailLocation": null,
      "kml": null,
      "kmlVost": null,
      "pco": null,
      "cos": null,
      "heliFight": 0,
      "heliCoord": 0,
      "planeFight": 0,
      "anepcDirectUpdate": false,
      "regiao": "Norte",
      "sub_regiao": "Tâmega e Sousa",
      "created": {
        "sec": 1696667653
      },
      "updated": {
        "sec": 1696670049
      }
    },
    {
      "_id": {
        "$id": "65211f281832d540a108e302"
      },
      "id": "20231239535",
      "coords": true,
      "dateTime": {
        "sec": 1696669080
      },
      "date": "07-10-2023",
      "hour": "09:58",
      "location": "Porto, Maia, Castêlo Da Maia",
      "aerial": 0,
      "meios_aquaticos": 0,
      "man": 4,
      "terrain": 1,
      "district": "Porto",
      "concelho": "Maia",
      "freguesia": "Castêlo Da Maia",
      "dico": "1306",
      "lat": 41.272128,
      "lng": -8.631388,
      "naturezaCode": "3103",
      "natureza": "Mato",
      "especieName": null,
      "familiaName": null,
      "statusCode": 4,
      "statusColor": "FF6E02",
      "status": "Despacho de 1º Alerta",
      "important": false,
      "localidade": "Castêlo Da Maia ",
      "active": true,
      "sadoId": "20231239535",
      "sharepointId": 22746052,
      "extra": null,
      "disappear": false,
      "icnf": null,
      "detailLocation": null,
      "kml": null,
      "kmlVost": null,
      "pco": null,
      "cos": null,
      "heliFight": 0,
      "heliCoord": 0,
      "planeFight": 0,
      "anepcDirectUpdate": false,
      "regiao": "Norte",
      "sub_regiao": "Area M. Porto",
      "created": {
        "sec": 1696669480
      },
      "updated": {
        "sec": 1696670656
      }
    },
    {
      "_id": {
        "$id": "6521242c1832d540a108e31a"
      },
      "id": "20231239643",
      "coords": true,
      "dateTime": {
        "sec": 1696670460
      },
      "date": "07-10-2023",
      "hour": "10:21",
      "location": "Porto, Felgueiras, Vila Fria E Vizela (São Jorge)",
      "aerial": 0,
      "meios_aquaticos": 0,
      "man": 0,
      "terrain": 0,
      "district": "Porto",
      "concelho": "Felgueiras",
      "freguesia": "Vila Fria E Vizela (São Jorge)",
      "dico": "1303",
      "lat": 41.3875,
      "lng": -8.24143,
      "naturezaCode": "3103",
      "natureza": "Mato",
      "especieName": null,
      "familiaName": null,
      "statusCode": 3,
      "statusColor": "FF6E02",
      "status": "Despacho",
      "important": false,
      "localidade": "União Das Freguesias De Vila Fria E Vizela (São Jorge) ",
      "active": true,
      "sadoId": "20231239643",
      "sharepointId": 22746160,
      "extra": null,
      "disappear": false,
      "icnf": null,
      "detailLocation": null,
      "kml": null,
      "kmlVost": null,
      "pco": null,
      "cos": null,
      "heliFight": 0,
      "heliCoord": 0,
      "planeFight": 0,
      "anepcDirectUpdate": false,
      "regiao": "Norte",
      "sub_regiao": "Tâmega e Sousa",
      "created": {
        "sec": 1696670764
      },
      "updated": {
        "sec": 1696670775
      }
    }
  ]
}
