{
  "success": true,
  "data": [
    {
      "_id": {
        "$id": "67d09bce34e7971bb41f4d23"
      },
      "id": "20250316849",
      "coords": true,
      "dateTime": {
        "sec": 1741724220
      },
      "date": "11-03-2025",
      "hour": "20:17",
      "location": "Faro, Vila Real de Santo António, Vila Nova De Cacela",
      "aerial": 0,
      "meios_aquaticos": 0,
      "man": 9,
      "terrain": 3,
      "district": "Faro",
      "concelho": "Vila Real De Santo António",
      "freguesia": "Vila Nova De Cacela",
      "dico": "0816",
      "lat": 37.167748,
      "lng": -7.529578,
      "naturezaCode": "3103",
      "natureza": "Mato",
      "especieName": null,
      "familiaName": null,
      "statusCode": 8,
      "statusColor": "BDBDBD",
      "status": "Conclusão",
      "important": false,
      "localidade": "Manta Rota ",
      "active": true,
      "sadoId": "20250316849",
      "sharepointId": 25073511,
      "extra": null,
      "disappear": false,
      "icnf": null,
      "detailLocation": null,
      "kml": null,
      "kmlVost": null,
      "pco": null,
      "cos": null,
      "heliFight": 0,
      "heliCoord": 0,
      "planeFight": 0,
      "anepcDirectUpdate": false,
      "regiao": "Algarve",
      "sub_regiao": "Algarve",
      "created": {
        "sec": 1741724622
      },
      "updated": {
        "sec": 1741726917
      }
    }
  ]
}
