{
  "success": true,
  "data": [
    {
      "_id": {
        "$id": "687e6ed5a0e41439561040d2"
      },
      "id": "20250955650",
      "coords": true,
      "dateTime": {
        "sec": 1753115880
      },
      "date": "21-07-2025",
      "hour": "17:38",
      "location": "Setúbal, Santiago do Cacém, Cercal",
      "aerial": 0,
      "meios_aquaticos": 0,
      "man": 0,
      "terrain": 0,
      "district": "Setúbal",
      "concelho": "Santiago Do Cacém",
      "freguesia": "Cercal",
      "dico": "1509",
      "lat": 37.791582,
      "lng": -8.682272,
      "naturezaCode": "3103",
      "natureza": "Mato",
      "especieName": null,
      "familiaName": null,
      "statusCode": 9,
      "statusColor": "6ABF59",
      "status": "Vigilância",
      "important": false,
      "localidade": "Cercal ",
      "active": true,
      "sadoId": "20250955650",
      "sharepointId": 25712338,
      "extra": null,
      "disappear": false,
      "icnf": null,
      "detailLocation": null,
      "kml": null,
      "kmlVost": null,
      "pco": null,
      "cos": null,
      "heliFight": 0,
      "heliCoord": 0,
      "planeFight": 0,
      "anepcDirectUpdate": false,
      "regiao": "Alentejo",
      "sub_regiao": "Alentejo Litoral",
      "created": {
        "sec": 1753116373
      },
      "updated": {
        "sec": 1753468572
      }
    },
    {
      "_id": {
        "$id": "68826176a0e94431b5797be0"
      },
      "id": "20250970568",
      "coords": true,
      "dateTime": {
        "sec": 1753375200
      },
      "date": "24-07-2025",
      "hour": "17:40",
      "location": "Viseu, Cinfães, Santiago De Piães",
      "aerial": 0,
      "meios_aquaticos": 0,
      "man": 45,
      "terrain": 14,
      "district": "Viseu",
      "concelho": "Cinfães",
      "freguesia": "Santiago De Piães",
      "dico": "1804",
      "lat": 41.025392,
      "lng": -8.173138,
      "naturezaCode": "3103",
      "natureza": "Mato",
      "especieName": null,
      "familiaName": null,
      "statusCode": 8,
      "statusColor": "BDBDBD",
      "status": "Conclusão",
      "important": false,
      "localidade": " ",
      "active": true,
      "sadoId": "20250970568",
      "sharepointId": 25727257,
      "extra": null,
      "disappear": false,
      "icnf": null,
      "detailLocation": null,
      "kml": null,
      "kmlVost": null,
      "pco": null,
      "cos": null,
      "heliFight": 0,
      "heliCoord": 0,
      "planeFight": 0,
      "anepcDirectUpdate": false,
      "regiao": "Norte",
      "sub_regiao": "Tâmega e Sousa",
      "created": {
        "sec": 1753375094
      },
      "updated": {
        "sec": 1753476013
      }
    },
    {
      "_id": {
        "$id": "6882ab0d913175377b5bde2e"
      },
      "id": "20250971811",
      "coords": true,
      "dateTime": {
        "sec": 1753393680
      },
      "date": "24-07-2025",
      "hour": "22:48",
      "location": "Guarda, Guarda, Vila Fernando",
      "aerial": 0,
      "meios_aquaticos": 0,
      "man": 5,
      "terrain": 1,
      "district": "Guarda",
      "concelho": "Guarda",
      "freguesia": "Vila Fernando",
      "dico": "0907",
      "lat": 40.491237,
      "lng": -7.165667,
      "naturezaCode": "3103",
      "natureza": "Mato",
      "especieName": null,
      "familiaName": null,
      "statusCode": 9,
      "statusColor": "6ABF59",
      "status": "Vigilância",
      "important": false,
      "localidade": "Vila Fernando ",
      "active": true,
      "sadoId": "20250971811",
      "sharepointId": 25728500,
      "extra": null,
      "disappear": false,
      "icnf": {
        "altitude": 769.227,
        "fogacho": true,
        "fontealerta": "112"
      },
      "detailLocation": "Vila Fernando",
      "kml": null,
      "kmlVost": null,
      "pco": null,
      "cos": null,
      "heliFight": 0,
      "heliCoord": 0,
      "planeFight": 0,
      "anepcDirectUpdate": false,
      "regiao": "Centro",
      "sub_regiao": "Beiras e Serra da Estrela",
      "created": {
        "sec": 1753393933
      },
      "updated": {
        "sec": 1753473974
      }
    },
    {
      "_id": {
        "$id": "6882b73c8575c122777ae6fa"
      },
      "id": "20250971957",
      "coords": true,
      "dateTime": {
        "sec": 1753396740
      },
      "date": "24-07-2025",
      "hour": "23:39",
      "location": "Guarda, Guarda, Vila Fernando",
      "aerial": 0,
      "meios_aquaticos": 0,
      "man": 10,
      "terrain": 2,
      "district": "Guarda",
      "concelho": "Guarda",
      "freguesia": "Vila Fernando",
      "dico": "0907",
      "lat": 40.484042,
      "lng": -7.135077,
      "naturezaCode": "3103",
      "natureza": "Mato",
      "especieName": null,
      "familiaName": null,
      "statusCode": 9,
      "statusColor": "6ABF59",
      "status": "Vigilância",
      "important": false,
      "localidade": "Vila Fernando          ",
      "active": true,
      "sadoId": "20250971957",
      "sharepointId": 25728646,
      "extra": null,
      "disappear": false,
      "icnf": null,
      "detailLocation": null,
      "kml": null,
      "kmlVost": null,
      "pco": null,
      "cos": null,
      "heliFight": 0,
      "heliCoord": 0,
      "planeFight": 0,
      "anepcDirectUpdate": false,
      "regiao": "Centro",
      "sub_regiao": "Beiras e Serra da Estrela",
      "created": {
        "sec": 1753397052
      },
      "updated": {
        "sec": 1753479021
      }
    },
    {
      "_id": {
        "$id": "6882fef853c312091125f943"
      },
      "id": "20250972393",
      "coords": true,
      "dateTime": {
        "sec": 1753415100
      },
      "date": "25-07-2025",
      "hour": "04:45",
      "location": "Viana Do Castelo, Arcos de Valdevez, São Jorge E Ermelo",
      "aerial": 0,
      "meios_aquaticos": 0,
      "man": 117,
      "terrain": 36,
      "district": "Viana Do Castelo",
      "concelho": "Arcos De Valdevez",
      "freguesia": "São Jorge E Ermelo",
      "dico": "1601",
      "lat": 41.818005,
      "lng": -8.356835,
      "naturezaCode": "3101",
      "natureza": "Povoamento Florestal",
      "especieName": null,
      "familiaName": null,
      "statusCode": 8,
      "statusColor": "BDBDBD",
      "status": "Conclusão",
      "important": false,
      "localidade": "Gração ",
      "active": true,
      "sadoId": "20250972393",
      "sharepointId": 25729082,
      "extra": null,
      "disappear": false,
      "icnf": null,
      "detailLocation": null,
      "kml": null,
      "kmlVost": null,
      "pco": null,
      "cos": null,
      "heliFight": 0,
      "heliCoord": 0,
      "planeFight": 0,
      "anepcDirectUpdate": false,
      "regiao": "Norte",
      "sub_regiao": "Alto Minho",
      "created": {
        "sec": 1753415416
      },
      "updated": {
        "sec": 1753478775
      }
    },
    {
      "_id": {
        "$id": "688349fe5a7b48706215049c"
      },
      "id": "20250973367",
      "coords": true,
      "dateTime": {
        "sec": 1753434300
      },
      "date": "25-07-2025",
      "hour": "10:05",
      "location": "Viseu, Cinfães, Santiago De Piães",
      "aerial": 0,
      "meios_aquaticos": 0,
      "man": 5,
      "terrain": 1,
      "district": "Viseu",
      "concelho": "Cinfães",
      "freguesia": "Santiago De Piães",
      "dico": "1804",
      "lat": 41.04848,
      "lng": -8.167988,
      "naturezaCode": "3103",
      "natureza": "Mato",
      "especieName": null,
      "familiaName": null,
      "statusCode": 8,
      "statusColor": "BDBDBD",
      "status": "Conclusão",
      "important": false,
      "localidade": "Vilarinho ",
      "active": true,
      "sadoId": "20250973367",
      "sharepointId": 25730056,
      "extra": null,
      "disappear": false,
      "icnf": null,
      "detailLocation": null,
      "kml": null,
      "kmlVost": null,
      "pco": null,
      "cos": null,
      "heliFight": 0,
      "heliCoord": 0,
      "planeFight": 0,
      "anepcDirectUpdate": false,
      "regiao": "Norte",
      "sub_regiao": "Tâmega e Sousa",
      "created": {
        "sec": 1753434622
      },
      "updated": {
        "sec": 1753474934
      }
    },
    {
      "_id": {
        "$id": "68836619d602e7490159012b"
      },
      "id": "20250974143",
      "coords": true,
      "dateTime": {
        "sec": 1753441620
      },
      "date": "25-07-2025",
      "hour": "12:07",
      "location": "Bragança, Bragança, Aveleda E Rio De Onor",
      "aerial": 0,
      "meios_aquaticos": 0,
      "man": 144,
      "terrain": 48,
      "district": "Bragança",
      "concelho": "Bragança",
      "freguesia": "Aveleda E Rio De Onor",
      "dico": "0402",
      "lat": 41.891435,
      "lng": -6.707873,
      "naturezaCode": "3103",
      "natureza": "Mato",
      "especieName": null,
      "familiaName": null,
      "statusCode": 8,
      "statusColor": "BDBDBD",
      "status": "Conclusão",
      "important": false,
      "localidade": "Aveleda ",
      "active": true,
      "sadoId": "20250974143",
      "sharepointId": 25730832,
      "extra": null,
      "disappear": false,
      "icnf": null,
      "detailLocation": null,
      "kml": null,
      "kmlVost": null,
      "pco": null,
      "cos": null,
      "heliFight": 0,
      "heliCoord": 0,
      "planeFight": 0,
      "anepcDirectUpdate": false,
      "regiao": "Norte",
      "sub_regiao": "Terras de Trás-os-Montes",
      "created": {
        "sec": 1753441817
      },
      "updated": {
        "sec": 1753478660
      }
    },
    {
      "_id": {
        "$id": "688391aef9994e13fd315397"
      },
      "id": "20250975116",
      "coords": true,
      "dateTime": {
        "sec": 1753452600
      },
      "date": "25-07-2025",
      "hour": "15:10",
      "location": "Vila Real, Peso da Régua, Poiares E Canelas",
      "aerial": 0,
      "meios_aquaticos": 0,
      "man": 24,
      "terrain": 7,
      "district": "Vila Real",
      "concelho": "Peso Da Régua",
      "freguesia": "Poiares E Canelas",
      "dico": "1708",
      "lat": 41.192565,
      "lng": -7.726247,
      "naturezaCode": "3103",
      "natureza": "Mato",
      "especieName": null,
      "familiaName": null,
      "statusCode": 9,
      "statusColor": "6ABF59",
      "status": "Vigilância",
      "important": false,
      "localidade": "Quinta Da Seara De Ordens ",
      "active": true,
      "sadoId": "20250975116",
      "sharepointId": 25731805,
      "extra": null,
      "disappear": false,
      "icnf": {
        "altitude": 503.924,
        "fogacho": true,
        "fontealerta": "112"
      },
      "detailLocation": "L (POIARES)",
      "kml": null,
      "kmlVost": null,
      "pco": null,
      "cos": null,
      "heliFight": 0,
      "heliCoord": 0,
      "planeFight": 0,
      "anepcDirectUpdate": false,
      "regiao": "Norte",
      "sub_regiao": "Douro",
      "created": {
        "sec": 1753452974
      },
      "updated": {
        "sec": 1753472535
      }
    },
    {
      "_id": {
        "$id": "688397a47988cf3f950e0e6d"
      },
      "id": "20250975266",
      "coords": true,
      "dateTime": {
        "sec": 1753454160
      },
      "date": "25-07-2025",
      "hour": "15:36",
      "location": "Braga, Guimarães, Briteiros Santo Estêvão E Donim",
      "aerial": 0,
      "meios_aquaticos": 0,
      "man": 12,
      "terrain": 3,
      "district": "Braga",
      "concelho": "Guimarães",
      "freguesia": "Briteiros Santo Estêvão E Donim",
      "dico": "0308",
      "lat": 41.521391,
      "lng": -8.30805,
      "naturezaCode": "3103",
      "natureza": "Mato",
      "especieName": null,
      "familiaName": null,
      "statusCode": 8,
      "statusColor": "BDBDBD",
      "status": "Conclusão",
      "important": false,
      "localidade": " ",
      "active": true,
      "sadoId": "20250975266",
      "sharepointId": 25731955,
      "extra": null,
      "disappear": false,
      "icnf": null,
      "detailLocation": null,
      "kml": null,
      "kmlVost": null,
      "pco": null,
      "cos": null,
      "heliFight": 0,
      "heliCoord": 0,
      "planeFight": 0,
      "anepcDirectUpdate": false,
      "regiao": "Norte",
      "sub_regiao": "Ave",
      "created": {
        "sec": 1753454500
      },
      "updated": {
        "sec": 1753478660
      }
    },
    {
      "_id": {
        "$id": "6883a6c6c537ee37f740140f"
      },
      "id": "20250975625",
      "coords": true,
      "dateTime": {
        "sec": 1753457880
      },
      "date": "25-07-2025",
      "hour": "16:38",
      "location": "Beja, Beja, Albernoa E Trindade",
      "aerial": 0,
      "meios_aquaticos": 0,
      "man": 0,
      "terrain": 0,
      "district": "Beja",
      "concelho": "Beja",
      "freguesia": "Albernoa E Trindade",
      "dico": "0205",
      "lat": 37.910075,
      "lng": -7.869855,
      "naturezaCode": "3105",
      "natureza": "Agrícola",
      "especieName": null,
      "familiaName": null,
      "statusCode": 9,
      "statusColor": "6ABF59",
      "status": "Vigilância",
      "important": false,
      "localidade": "Herdade Da Matosa ",
      "active": true,
      "sadoId": "20250975625",
      "sharepointId": 25732314,
      "extra": null,
      "disappear": false,
      "icnf": {
        "altitude": 94.1537,
        "agricola": true,
        "fontealerta": "Bombeiros"
      },
      "detailLocation": "IP2 (Barranco das Vendas)",
      "kml": null,
      "kmlVost": null,
      "pco": null,
      "cos": null,
      "heliFight": 0,
      "heliCoord": 0,
      "planeFight": 0,
      "anepcDirectUpdate": false,
      "regiao": "Alentejo",
      "sub_regiao": "Baixo Alentejo",
      "created": {
        "sec": 1753458374
      },
      "updated": {
        "sec": 1753470371
      }
    },
    {
      "_id": {
        "$id": "6883c79b02b1955e0f143f56"
      },
      "id": "20250976299",
      "coords": true,
      "dateTime": {
        "sec": 1753466160
      },
      "date": "25-07-2025",
      "hour": "18:56",
      "location": "Beja, Castro Verde, Castro Verde E Casével",
      "aerial": 0,
      "meios_aquaticos": 0,
      "man": 9,
      "terrain": 3,
      "district": "Beja",
      "concelho": "Castro Verde",
      "freguesia": "Castro Verde E Casével",
      "dico": "0206",
      "lat": 37.720679,
      "lng": -8.194323,
      "naturezaCode": "3105",
      "natureza": "Agrícola",
      "especieName": null,
      "familiaName": null,
      "statusCode": 7,
      "statusColor": "6ABF59",
      "status": "Em Resolução",
      "important": false,
      "localidade": "Cerro Da Cabeça Gorda ",
      "active": true,
      "sadoId": "20250976299",
      "sharepointId": 25732988,
      "extra": null,
      "disappear": false,
      "icnf": null,
      "detailLocation": null,
      "kml": null,
      "kmlVost": null,
      "pco": null,
      "cos": null,
      "heliFight": 0,
      "heliCoord": 0,
      "planeFight": 0,
      "anepcDirectUpdate": false,
      "regiao": "Alentejo",
      "sub_regiao": "Baixo Alentejo",
      "created": {
        "sec": 1753466779
      },
      "updated": {
        "sec": 1753472536
      }
    },
    {
      "_id": {
        "$id": "6883cf9302b1955e0f14403c"
      },
      "id": "20250976458",
      "coords": true,
      "dateTime": {
        "sec": 1753468680
      },
      "date": "25-07-2025",
      "hour": "19:38",
      "location": "Aveiro, Aveiro, Requeixo, Nossa Senhora De Fátima E Nariz",
      "aerial": 0,
      "meios_aquaticos": 0,
      "man": 20,
      "terrain": 7,
      "district": "Aveiro",
      "concelho": "Aveiro",
      "freguesia": "Requeixo, Nossa Senhora De Fátima E Nariz",
      "dico": "0105",
      "lat": 40.57098,
      "lng": -8.58724,
      "naturezaCode": "3101",
      "natureza": "Povoamento Florestal",
      "especieName": null,
      "familiaName": null,
      "statusCode": 8,
      "statusColor": "BDBDBD",
      "status": "Conclusão",
      "important": false,
      "localidade": "Póvoa Do Valado ",
      "active": true,
      "sadoId": "20250976458",
      "sharepointId": 25733147,
      "extra": null,
      "disappear": false,
      "icnf": null,
      "detailLocation": null,
      "kml": null,
      "kmlVost": null,
      "pco": null,
      "cos": null,
      "heliFight": 0,
      "heliCoord": 0,
      "planeFight": 0,
      "anepcDirectUpdate": false,
      "regiao": "Centro",
      "sub_regiao": "Região de Aveiro",
      "created": {
        "sec": 1753468819
      },
      "updated": {
        "sec": 1753477942
      }
    },
    {
      "_id": {
        "$id": "6883e3b65039700915346b32"
      },
      "id": "20250976838",
      "coords": true,
      "dateTime": {
        "sec": 1753473720
      },
      "date": "25-07-2025",
      "hour": "21:02",
      "location": "Portalegre, Sousel, Cano",
      "aerial": 0,
      "meios_aquaticos": 0,
      "man": 12,
      "terrain": 3,
      "district": "Portalegre",
      "concelho": "Sousel",
      "freguesia": "Cano",
      "dico": "1215",
      "lat": 38.957972,
      "lng": -7.745368,
      "naturezaCode": "3105",
      "natureza": "Agrícola",
      "especieName": null,
      "familiaName": null,
      "statusCode": 8,
      "statusColor": "BDBDBD",
      "status": "Conclusão",
      "important": false,
      "localidade": "Monte Da Roça ",
      "active": true,
      "sadoId": "20250976838",
      "sharepointId": 25733527,
      "extra": null,
      "disappear": false,
      "icnf": {
        "altitude": 196.988,
        "agricola": true,
        "fontealerta": "Populares"
      },
      "detailLocation": "Monte da Roça (ED372 (ED372) Km 20)",
      "kml": null,
      "kmlVost": null,
      "pco": null,
      "cos": null,
      "heliFight": 0,
      "heliCoord": 0,
      "planeFight": 0,
      "anepcDirectUpdate": false,
      "regiao": "Alentejo",
      "sub_regiao": "Alto Alentejo",
      "created": {
        "sec": 1753473974
      },
      "updated": {
        "sec": 1753476565
      }
    },
    {
      "_id": {
        "$id": "6883e8deb829f36aad205d36"
      },
      "id": "20250976931",
      "coords": true,
      "dateTime": {
        "sec": 1753474860
      },
      "date": "25-07-2025",
      "hour": "21:21",
      "location": "Santarém, Salvaterra de Magos, Muge",
      "aerial": 0,
      "meios_aquaticos": 0,
      "man": 32,
      "terrain": 10,
      "district": "Santarém",
      "concelho": "Salvaterra De Magos",
      "freguesia": "Muge",
      "dico": "1415",
      "lat": 39.084927,
      "lng": -8.717905,
      "naturezaCode": "3103",
      "natureza": "Mato",
      "especieName": null,
      "familiaName": null,
      "statusCode": 8,
      "statusColor": "BDBDBD",
      "status": "Conclusão",
      "important": false,
      "localidade": "Muge ",
      "active": true,
      "sadoId": "20250976931",
      "sharepointId": 25733620,
      "extra": null,
      "disappear": false,
      "icnf": null,
      "detailLocation": null,
      "kml": null,
      "kmlVost": null,
      "pco": null,
      "cos": null,
      "heliFight": 0,
      "heliCoord": 0,
      "planeFight": 0,
      "anepcDirectUpdate": false,
      "regiao": "Lisboa e Vale do Tejo",
      "sub_regiao": "Lezíria do Tejo",
      "created": {
        "sec": 1753475294
      },
      "updated": {
        "sec": 1753478053
      }
    },
    {
      "_id": {
        "$id": "6883ebadb829f36aad205d56"
      },
      "id": "20250976996",
      "coords": true,
      "dateTime": {
        "sec": 1753475760
      },
      "date": "25-07-2025",
      "hour": "21:36",
      "location": "Aveiro, Santa Maria da Feira, Caldas De São Jorge E Pigeiros",
      "aerial": 0,
      "meios_aquaticos": 0,
      "man": 5,
      "terrain": 1,
      "district": "Aveiro",
      "concelho": "Santa Maria Da Feira",
      "freguesia": "Caldas De São Jorge E Pigeiros",
      "dico": "0109",
      "lat": 40.97093,
      "lng": -8.500571,
      "naturezaCode": "3103",
      "natureza": "Mato",
      "especieName": null,
      "familiaName": null,
      "statusCode": 8,
      "statusColor": "BDBDBD",
      "status": "Conclusão",
      "important": false,
      "localidade": "União Das Freguesias De Caldas De São Jorge E Pigeiros ",
      "active": true,
      "sadoId": "20250976996",
      "sharepointId": 25733685,
      "extra": null,
      "disappear": false,
      "icnf": null,
      "detailLocation": null,
      "kml": null,
      "kmlVost": null,
      "pco": null,
      "cos": null,
      "heliFight": 0,
      "heliCoord": 0,
      "planeFight": 0,
      "anepcDirectUpdate": false,
      "regiao": "Norte",
      "sub_regiao": "Area M. Porto",
      "created": {
        "sec": 1753476013
      },
      "updated": {
        "sec": 1753477578
      }
    },
    {
      "_id": {
        "$id": "6883f604ca72a47984117d61"
      },
      "id": "20250977135",
      "coords": true,
      "dateTime": {
        "sec": 1753477740
      },
      "date": "25-07-2025",
      "hour": "22:09",
      "location": "Lisboa, Mafra, Malveira E São Miguel De Alcainça",
      "aerial": 0,
      "meios_aquaticos": 0,
      "man": 12,
      "terrain": 3,
      "district": "Lisboa",
      "concelho": "Mafra",
      "freguesia": "Malveira E São Miguel De Alcainça",
      "dico": "1109",
      "lat": 38.919433,
      "lng": -9.288438,
      "naturezaCode": "3103",
      "natureza": "Mato",
      "especieName": null,
      "familiaName": null,
      "statusCode": 8,
      "statusColor": "BDBDBD",
      "status": "Conclusão",
      "important": false,
      "localidade": "Alcainça ",
      "active": true,
      "sadoId": "20250977135",
      "sharepointId": 25733824,
      "extra": null,
      "disappear": false,
      "icnf": {
        "altitude": 216.483,
        "fogacho": true,
        "fontealerta": "Populares"
      },
      "detailLocation": "Perto do Campo da Bola (Alcainça)",
      "kml": null,
      "kmlVost": null,
      "pco": null,
      "cos": null,
      "heliFight": 0,
      "heliCoord": 0,
      "planeFight": 0,
      "anepcDirectUpdate": false,
      "regiao": "Lisboa e Vale do Tejo",
      "sub_regiao": "Grande Lisboa",
      "created": {
        "sec": 1753478660
      },
      "updated": {
        "sec": 1753479135
      }
    },
    {
      "_id": {
        "$id": "6883f8cfca72a47984117d83"
      },
      "id": "20250977173",
      "coords": true,
      "dateTime": {
        "sec": 1753478820
      },
      "date": "25-07-2025",
      "hour": "22:27",
      "location": "Beja, Beja, Beja (Santiago Maior E São João Baptista)",
      "aerial": 0,
      "meios_aquaticos": 0,
      "man": 16,
      "terrain": 4,
      "district": "Beja",
      "concelho": "Beja",
      "freguesia": "Beja (Santiago Maior E São João Baptista)",
      "dico": "0205",
      "lat": 38.014111,
      "lng": -7.87003,
      "naturezaCode": "3105",
      "natureza": "Agrícola",
      "especieName": null,
      "familiaName": null,
      "statusCode": 8,
      "statusColor": "BDBDBD",
      "status": "Conclusão",
      "important": false,
      "localidade": "Beja 1º ",
      "active": true,
      "sadoId": "20250977173",
      "sharepointId": 25733862,
      "extra": null,
      "disappear": false,
      "icnf": {
        "altitude": 213.833,
        "agricola": true,
        "fontealerta": "Populares"
      },
      "detailLocation": "Bairro dos Moinhos (BEJA 1º)",
      "kml": null,
      "kmlVost": null,
      "pco": null,
      "cos": null,
      "heliFight": 0,
      "heliCoord": 0,
      "planeFight": 0,
      "anepcDirectUpdate": false,
      "regiao": "Alentejo",
      "sub_regiao": "Baixo Alentejo",
      "created": {
        "sec": 1753479375
      },
      "updated": {
        "sec": 1753479734
      }
    }
  ]
}
